DUMP/BACKUP2_closestConnectedDistance.py
DUMP/BACKUP3_closestConnectedDistance.py
DUMP/Copy of flatFieldFromImgFit.py
DUMP/DOESNTWORKGOOD_INCL_FINE_DIST_MEAS_closestConnectedDistance.py
DUMP/filterIfNeighboursTooLow.py
DUMP/FitHistogramPeaks_backup.py
DUMP/FitHistogramPeaks_removed.py
DUMP/OLD_QuadDetection.py
DUMP/removeSingleTimeEvents.py
DUMP/test.py
DUMP/toFloatArray.py
DUMP/zDenoise.py
DUMP/_BACKUPclosestConnectedDistance.py
DUMP/_DOESNTWORK_fit2dStructuredIDW.py
DUMP/_removed_fromPerspectiveCorrection.py
DUMP/_removed_fromPolyLinesFromContourImg.py
DUMP/__init__.py
imgProcessor/alignImageAlongLine.py
imgProcessor/baseClasses.py
imgProcessor/calcAspectRatioFromCorners.py
imgProcessor/decompHomography.py
imgProcessor/equalizeImage.py
imgProcessor/exceptions.py
imgProcessor/FitHistogramPeaks.py
imgProcessor/genericCameraMatrix.py
imgProcessor/imgAverage.py
imgProcessor/imgIO.py
imgProcessor/imgPointToWorldCoord.py
imgProcessor/linearBlend.py
imgProcessor/minimumLineInArray.py
imgProcessor/PatternRecognition.py
imgProcessor/PerspectiveTransformation.py
imgProcessor/QuadDetection.py
imgProcessor/scaleSignal.py
imgProcessor/signal.py
imgProcessor/SingleTimeEffectDetection.py
imgProcessor/sortCorners.py
imgProcessor/StitchImages.py
imgProcessor/tests.py
imgProcessor/transformations.py
imgProcessor/webcamTakePhotos.py
imgProcessor/__init__.py
imgProcessor/array/subCell2D.py
imgProcessor/array/__init__.py
imgProcessor/camera/CameraCalibration.py
imgProcessor/camera/DarkCurrentMap.py
imgProcessor/camera/flatFieldFromCalibration.py
imgProcessor/camera/FlatFieldFromImgFit.py
imgProcessor/camera/LensDistortion.py
imgProcessor/camera/NoiseLevelFunction.py
imgProcessor/camera/PerspectiveCorrection.py
imgProcessor/camera/__init__.py
imgProcessor/camera/flatField/flatField.py
imgProcessor/camera/flatField/flatFieldFromCalibration.py
imgProcessor/camera/flatField/FlatFieldFromImgFit.py
imgProcessor-0.2.5.dist-info/DESCRIPTION.rst
imgProcessor-0.2.5.dist-info/METADATA
imgProcessor-0.2.5.dist-info/metadata.json
imgProcessor-0.2.5.dist-info/RECORD
imgProcessor-0.2.5.dist-info/top_level.txt
imgProcessor-0.2.5.dist-info/WHEEL
