Metadata-Version: 2.0
Name: imgProcessor
Version: 0.2.5
Summary: A collection of various image processing routines
Home-page: https://github.com/radjkarl/imgProcessor
Author: Karl Bedrich
Author-email: karl@bedrich.de
License: GPLv3
Platform: UNKNOWN
Classifier: Intended Audience :: Developers
Classifier: Intended Audience :: Science/Research
Classifier: Intended Audience :: Other Audience
Classifier: License :: OSI Approved :: GNU General Public License (GPL)
Classifier: Operating System :: OS Independent
Classifier: Programming Language :: Python
Classifier: Topic :: Scientific/Engineering :: Information Analysis
Classifier: Topic :: Scientific/Engineering :: Visualization
Classifier: Topic :: Software Development :: Libraries :: Python Modules
Requires-Dist: scikit-image
Requires-Dist: numpy
Requires-Dist: scipy
Requires-Dist: numba
Requires-Dist: transforms3d
